TensorflowXuexizhinan/README.md
TensorflowXuexizhinan/__init__.py
TensorflowXuexizhinan/__main__.py
TensorflowXuexizhinan/file.epub
TensorflowXuexizhinan/index.html
TensorflowXuexizhinan/css/__init__.py
TensorflowXuexizhinan/css/annotations.css
TensorflowXuexizhinan/css/main.css
TensorflowXuexizhinan/css/normalize.css
TensorflowXuexizhinan/css/popup.css
TensorflowXuexizhinan/font/__init__.py
TensorflowXuexizhinan/font/fontello.eot
TensorflowXuexizhinan/font/fontello.svg
TensorflowXuexizhinan/font/fontello.ttf
TensorflowXuexizhinan/font/fontello.woff
TensorflowXuexizhinan/img/__init__.py
TensorflowXuexizhinan/img/annotator-glyph-sprite.png
TensorflowXuexizhinan/img/annotator-icon-sprite.png
TensorflowXuexizhinan/img/apple-touch-icon.png
TensorflowXuexizhinan/img/cancelfullscreen.png
TensorflowXuexizhinan/img/close.png
TensorflowXuexizhinan/img/fullscreen.png
TensorflowXuexizhinan/img/loader.gif
TensorflowXuexizhinan/img/menu-icon.png
TensorflowXuexizhinan/img/save.png
TensorflowXuexizhinan/img/saved.png
TensorflowXuexizhinan/img/settings-s.png
TensorflowXuexizhinan/img/settings.png
TensorflowXuexizhinan/img/star.png
TensorflowXuexizhinan/js/__init__.py
TensorflowXuexizhinan/js/epub.js
TensorflowXuexizhinan/js/epub.min.js
TensorflowXuexizhinan/js/epub.min.map
TensorflowXuexizhinan/js/hooks.min.js
TensorflowXuexizhinan/js/hooks.min.map
TensorflowXuexizhinan/js/reader.js
TensorflowXuexizhinan/js/reader.js.map
TensorflowXuexizhinan/js/reader.min.js
TensorflowXuexizhinan/js/reader.min.map
TensorflowXuexizhinan/js/hooks/__init__.py
TensorflowXuexizhinan/js/hooks/extensions/__init__.py
TensorflowXuexizhinan/js/hooks/extensions/highlight.js
TensorflowXuexizhinan/js/libs/__init__.py
TensorflowXuexizhinan/js/libs/jquery.min.js
TensorflowXuexizhinan/js/libs/localforage.min.js
TensorflowXuexizhinan/js/libs/screenfull.js
TensorflowXuexizhinan/js/libs/screenfull.min.js
TensorflowXuexizhinan/js/libs/zip.min.js
TensorflowXuexizhinan/js/plugins/__init__.py
tensorflow_xuexizhinan-2024.3.3.0.dist-info/METADATA
tensorflow_xuexizhinan-2024.3.3.0.dist-info/WHEEL
tensorflow_xuexizhinan-2024.3.3.0.dist-info/entry_points.txt
tensorflow_xuexizhinan-2024.3.3.0.dist-info/top_level.txt
tensorflow_xuexizhinan-2024.3.3.0.dist-info/RECORD
